LICENSE
README.md
setup.py
django_formsets_inside_form/__init__.py
django_formsets_inside_form/forms.py
django_formsets_inside_form.egg-info/PKG-INFO
django_formsets_inside_form.egg-info/SOURCES.txt
django_formsets_inside_form.egg-info/dependency_links.txt
django_formsets_inside_form.egg-info/requires.txt
django_formsets_inside_form.egg-info/top_level.txt