Metadata-Version: 2.1
Name: django-formsets-inside-form
Version: 0.1.4
Summary: A library to handle formsets within forms in Django
Home-page: https://github.com/DeividHugo/django-formsets-inside-form
Author: Deivid Hugo
Author-email: deividhugoof@gmail.com
License: MIT
License-File: LICENSE
Requires-Dist: Django>=2.0
